Metadata-Version: 1.0
Name: some-distributions
Version: 0.1
Summary: Gaussian distributions
Home-page: UNKNOWN
Author: Nawal Yala
Author-email: UNKNOWN
License: UNKNOWN
Platform: UNKNOWN
